qbitaro/__init__.py
qbitaro/gates.py
qbitaro/main.py
qbitaro/register.py
qbitaro/superdense.py
qbitaro/teleportation.py
qbitaro/utils.py
qbitaro-0.1.0.dist-info/METADATA
qbitaro-0.1.0.dist-info/WHEEL
qbitaro-0.1.0.dist-info/top_level.txt
qbitaro-0.1.0.dist-info/RECORD
